pyrisklib/__init__.py
pyrisklib/rating_agency.py
pyrisklib/rating_mapper.py
pyrisklib-0.1.0.dist-info/licenses/LICENSE
pyrisklib-0.1.0.dist-info/METADATA
pyrisklib-0.1.0.dist-info/WHEEL
pyrisklib-0.1.0.dist-info/top_level.txt
pyrisklib-0.1.0.dist-info/RECORD
